MANIFEST.in
README.md
setup.py
svj_ntuple_processing/__init__.py
svj_ntuple_processing/systematics.py
svj_ntuple_processing.egg-info/PKG-INFO
svj_ntuple_processing.egg-info/SOURCES.txt
svj_ntuple_processing.egg-info/dependency_links.txt
svj_ntuple_processing.egg-info/not-zip-safe
svj_ntuple_processing.egg-info/requires.txt
svj_ntuple_processing.egg-info/top_level.txt
svj_ntuple_processing/include/VERSION
test/test_filters.py
test/test_systematics.py