Metadata-Version: 1.0
Name: svj-ntuple-processing
Version: 0.20
Summary: Description text
Home-page: https://github.com/tklijnsma/svj_ntuple_processing.git
Author: Thomas Klijnsma
Author-email: tklijnsm@gmail.com
License: BSD 3-Clause License
Platform: UNKNOWN
